{
  "mem": 827927,
  "mem.free": 427785,
  "processors": 4,
  "instance.uptime": 38407,
  "uptime": 45223,
  "systemload.average": -1.0,
  "heap.committed": 757248,
  "heap.init": 131072,
  "heap.used": 329462,
  "heap": 1840640,
  "nonheap.committed": 72368,
  "nonheap.init": 2496,
  "nonheap.used": 70679,
  "nonheap": 0,
  "threads.peak": 48,
  "threads.daemon": 45,
  "threads.totalStarted": 84,
  "threads": 48,
  "classes": 9524,
  "classes.loaded": 9524,
  "classes.unloaded": 0,
  "gc.ps_scavenge.count": 14,
  "gc.ps_scavenge.time": 226,
  "gc.ps_marksweep.count": 2,
  "gc.ps_marksweep.time": 98,
  "gauge.response.ef7deaca96d94cfeb21c1985c44525db.star-star": 11.0,
  "counter.status.200.ef7deaca96d94cfeb21c1985c44525db.star-star": 55,
  "counter.status.200.metrics": 67,
  "gauge.response.getcount": 8.0,
  "gauge.response.metrics": 1.0,
  "counter.speed.minute.ef7deaca96d94cfeb21c1985c44525db": 55,
  "counter.status.200.getcount": 28,
  "normalized.servo.rest.totaltime": 1.1502207166666665,
  "normalized.servo.rest.count": 0.08333333333333333,
  "gauge.servo.rest.min": 8.019817,
  "gauge.servo.rest.max": 32.514423,
  "normalized.servo.zuul.filter-simplehostroutingfilter": 0.0,
  "normalized.servo.zuul.filter-sendresponsefilter": 0.0,
  "normalized.servo.zuul.filter-servlet30wrapperfilter": 0.0,
  "normalized.servo.zuul.filter-formbodywrapperfilter": 0.0,
  "normalized.servo.zuul.filter-zuulprefilter": 0.0,
  "normalized.servo.zuul.filter-servletdetectionfilter": 0.0,
  "normalized.servo.zuul.filter-ribbonroutingfilter": 0.0,
  "normalized.servo.zuul.filter-zuulpostfilter": 0.0,
  "normalized.servo.zuul.filter-sendforwardfilter": 0.0,
  "normalized.servo.zuul.filter-debugfilter": 0.0,
  "normalized.servo.zuul.filter-predecorationfilter": 0.0,
  "normalized.servo.zuul.filter-urlroutefilter": 0.0,
  "normalized.servo.zuul.filter-senderrorfilter": 0.0,
  "httpsessions.max": -1,
  "httpsessions.active": 0,
  "datasource.primary.active": 0,
  "datasource.primary.usage": 0.0
}